{"type": "Feature", "stac_version": "1.0.0", "stac_extensions": ["https://stac-extensions.github.io/view/v1.0.0/schema.json", "https://stac-extensions.github.io/projection/v1.0.0/schema.json", "https://stac-extensions.github.io/eo/v1.0.0/schema.json", "https://stac-extensions.github.io/raster/v1.1.0/schema.json", "https://stac-extensions.github.io/grid/v1.0.0/schema.json", "https://stac-extensions.github.io/classification/v1.1.0/schema.json"], "id": "17/031331013322/1050010038C4D300", "properties": {"datetime": "2024-02-06 16:14:02Z", "platform": "GE01", "gsd": 0.5, "ard_metadata_version": "0.0.1", "catalog_id": "1050010038C4D300", "utm_zone": 17, "quadkey": "031331013322", "view:off_nadir": 26.5, "view:azimuth": 193.8, "view:incidence_angle": 60.4, "view:sun_azimuth": 150.4, "view:sun_elevation": 41.1, "proj:epsg": 32617, "proj:geometry": {"type": "Polygon", "coordinates": [[[325152.28271484375, 3123384.0942382812], [325156.25, 3123384.0942382812], [325156.25, 3119843.75], [324945.068359375, 3119843.75], [324948.73046875, 3123370.6665039062], [325152.28271484375, 3123384.0942382812]]]}, "grid:code": "MXRA-Z17-031331013322", "proj:bbox": [324945.068359375, 3119843.75, 325156.25, 3123384.0942382812], "tile:data_area": 0.7, "tile:clouds_area": 0.0, "tile:clouds_percent": 0}, "bbox": [-82.78393030965316, 28.19276593321587, -82.78128818156755, 28.224737202565105], "geometry": {"type": "Polygon", "coordinates": [[[-82.78185876271122, 28.224736675927957], [-82.78181834843537, 28.224737202565105], [-82.78128818156755, 28.192793945760368], [-82.78343882377322, 28.19276593321587], [-82.78393030965316, 28.22458848618495], [-82.78185876271122, 28.224736675927957]]]}, "links": [{"rel": "collection", "href": "../../../acquisition_collections/1050010038C4D300_collection.json", "type": "application/json"}, {"rel": "parent", "href": "../../../acquisition_collections/1050010038C4D300_collection.json", "type": "application/json"}, {"rel": "root", "href": "../../../order_collections/6559111709582503805_root_collection.json", "type": "application/json"}], "assets": {"data-mask": {"type": "application/geopackage+sqlite3", "title": "Data Mask", "href": "./1050010038C4D300-data-mask.gpkg", "roles": ["data-mask"]}, "cloud-mask-raster": {"type": "image/tiff; application=geotiff; profile=cloud-optimized", "title": "Cloud/Cloud Shadow Coverage Raster", "description": "thematic raster, 0 -> no data, 1 -> clear, 2 -> cloud, 3 -> cloud shadow", "href": "./1050010038C4D300-clouds.tif", "proj:bbox": [319843.75, 3119843.75, 325156.25, 3125156.25], "proj:shape": [2176, 2176], "proj:transform": [2.44140625, 0.0, 319843.75, 0.0, -2.44140625, 3125156.25, 0.0, 0.0, 1.0], "raster:bands": [{"classification:classes": [{"value": 0, "name": "nodata", "description": "NoData"}, {"value": 1, "name": "clear", "description": "Clear of clouds or shadows"}, {"value": 2, "name": "cloud", "description": "Clouds"}, {"value": 3, "name": "cloud_shadow", "description": "Cloud shadows"}]}], "roles": ["cloud", "cloud-shadow"]}, "cloud-mask": {"type": "application/geopackage+sqlite3", "href": "./1050010038C4D300-cloud-mask.gpkg", "title": "Cloud Polygons", "roles": ["cloud"]}, "cloud-shadow-mask": {"type": "application/geopackage+sqlite3", "href": "./1050010038C4D300-cloud-shadow-mask.gpkg", "title": "Cloud Shadow Polygons", "roles": ["cloud-shadow"]}, "healthy-vegetation-mask-raster": {"type": "image/tiff; application=geotiff; profile=cloud-optimized", "href": "./1050010038C4D300-healthy-vegetation.tif", "title": "Healthy Vegetation Mask", "proj:bbox": [319843.75, 3119843.75, 325156.25, 3125156.25], "proj:shape": [2844, 2844], "proj:transform": [1.8679676511954992, 0.0, 319843.75, 0.0, -1.8679676511954992, 3125156.25, 0.0, 0.0, 1.0], "roles": ["data"]}, "healthy-vegetation-mask": {"type": "application/geopackage+sqlite3", "href": "./1050010038C4D300-healthy-vegetation-mask.gpkg", "title": "Healthy Vegetation Polygons", "roles": ["data"]}, "ms_analytic": {"type": "image/tiff; application=geotiff; profile=cloud-optimized", "title": "Multispectral Image", "href": "./1050010038C4D300-ms.tif", "proj:bbox": [319843.75, 3119843.75, 325156.25, 3125156.25], "proj:shape": [2844, 2844], "proj:transform": [1.8679676511954992, 0.0, 319843.75, 0.0, -1.8679676511954992, 3125156.25, 0.0, 0.0, 1.0], "eo:bands": [{"name": "BAND_B", "common_name": "blue", "description": "Blue"}, {"name": "BAND_G", "common_name": "green", "description": "Green"}, {"name": "BAND_R", "common_name": "red", "description": "Red"}, {"name": "BAND_N", "common_name": "nir08", "description": "Near Infrared 1"}], "roles": ["data"]}, "ms-saturation-mask-raster": {"type": "image/tiff; application=geotiff; profile=cloud-optimized", "title": "Multispectral Pixel Saturation Mask", "href": "./1050010038C4D300-ms-saturation.tif", "proj:bbox": [319843.75, 3119843.75, 325156.25, 3125156.25], "proj:shape": [2844, 2844], "proj:transform": [1.8679676511954992, 0.0, 319843.75, 0.0, -1.8679676511954992, 3125156.25, 0.0, 0.0, 1.0], "roles": ["saturation"]}, "ms-saturation-mask": {"type": "application/geopackage+sqlite3", "href": "./1050010038C4D300-ms-saturation-mask.gpkg", "title": "MS Pixel Saturation Polygons", "roles": ["saturation"]}, "pan_analytic": {"type": "image/tiff; application=geotiff; profile=cloud-optimized", "title": "Panchromatic Image", "href": "./1050010038C4D300-pan.tif", "proj:bbox": [319843.75, 3119843.75, 325156.25, 3125156.25], "proj:shape": [11376, 11376], "proj:transform": [0.4669919127988748, 0.0, 319843.75, 0.0, -0.4669919127988748, 3125156.25, 0.0, 0.0, 1.0], "eo:bands": [{"name": "BAND_P", "description": "Pan"}], "roles": ["data"]}, "pan-flare-mask-raster": {"type": "image/tiff; application=geotiff; profile=cloud-optimized", "href": "./1050010038C4D300-pan-flare.tif", "title": "Pan Flare Mask", "proj:bbox": [319843.75, 3119843.75, 325156.25, 3125156.25], "proj:shape": [11376, 11376], "proj:transform": [0.4669919127988748, 0.0, 319843.75, 0.0, -0.4669919127988748, 3125156.25, 0.0, 0.0, 1.0], "roles": ["data"]}, "pan-flare-mask": {"type": "application/geopackage+sqlite3", "href": "./1050010038C4D300-pan-flare-mask.gpkg", "title": "Pan Flare Polygons", "roles": ["data"]}, "terrain-shadow-mask-raster": {"type": "image/tiff; application=geotiff; profile=cloud-optimized", "href": "./1050010038C4D300-terrain-shadows.tif", "title": "Terrain Shadow Mask", "proj:bbox": [319843.75, 3119843.75, 325156.25, 3125156.25], "proj:shape": [2844, 2844], "proj:transform": [1.8679676511954992, 0.0, 319843.75, 0.0, -1.8679676511954992, 3125156.25, 0.0, 0.0, 1.0], "roles": ["terrain-shadow"]}, "terrain-shadow-mask": {"type": "application/geopackage+sqlite3", "href": "./1050010038C4D300-terrain-shadow-mask.gpkg", "title": "Terrain Shadow Polygons", "roles": ["terrain-shadow"]}, "visual": {"type": "image/tiff; application=geotiff; profile=cloud-optimized", "title": "Visual Image", "href": "./1050010038C4D300-visual.tif", "proj:bbox": [319843.75, 3119843.75, 325156.25, 3125156.25], "proj:shape": [17408, 17408], "proj:transform": [0.30517578125, 0.0, 319843.75, 0.0, -0.30517578125, 3125156.25, 0.0, 0.0, 1.0], "eo:bands": [{"name": "BAND_R", "common_name": "red", "description": "Red"}, {"name": "BAND_G", "common_name": "green", "description": "Green"}, {"name": "BAND_B", "common_name": "blue", "description": "Blue"}], "roles": ["visual"]}, "water-mask-raster": {"type": "image/tiff; application=geotiff; profile=cloud-optimized", "href": "./1050010038C4D300-water.tif", "title": "Water Mask", "proj:bbox": [319843.75, 3119843.75, 325156.25, 3125156.25], "proj:shape": [2844, 2844], "proj:transform": [1.8679676511954992, 0.0, 319843.75, 0.0, -1.8679676511954992, 3125156.25, 0.0, 0.0, 1.0], "roles": ["water-mask"]}, "water-mask": {"type": "application/geopackage+sqlite3", "href": "./1050010038C4D300-water-mask.gpkg", "title": "Water Polygons", "roles": ["water-mask"]}}, "collection": "1050010038C4D300"}